reverse_read/__init__.py
reverse_read/data.py
reverse_read/reverse_read.py
reverse_read-0.2.dist-info/LICENSE
reverse_read-0.2.dist-info/METADATA
reverse_read-0.2.dist-info/WHEEL
reverse_read-0.2.dist-info/top_level.txt
reverse_read-0.2.dist-info/RECORD
