Metadata-Version: 2.1
Name: reverse-read
Version: 0.2
Summary: A package for read reversed texts.
Home-page: https://github.com/pourya90091/reverse-read
Author: pourya90091
Author-email: pourya90091@gmail.com
Project-URL: Bug Tracker, https://github.com/pourya90091/reverse-read/issues
Classifier: Programming Language :: Python :: 3
Classifier: License :: OSI Approved :: MIT License
Classifier: Operating System :: OS Independent
Requires-Python: >=3.6
License-File: LICENSE
